mcpunk/__init__.py
mcpunk/dependencies.py
mcpunk/file_breakdown.py
mcpunk/file_chunk.py
mcpunk/file_chunkers.py
mcpunk/git_analysis.py
mcpunk/python_file_analysis.py
mcpunk/run_mcp_server.py
mcpunk/settings.py
mcpunk/tools.py
mcpunk/unset.py
mcpunk/util.py
mcpunk-0.12.0.dist-info/METADATA
mcpunk-0.12.0.dist-info/WHEEL
mcpunk-0.12.0.dist-info/entry_points.txt
mcpunk-0.12.0.dist-info/licenses/LICENSE
mcpunk-0.12.0.dist-info/RECORD
