Metadata-Version: 2.4
Name: mcpunk
Version: 0.12.0
Summary: MCP tools for Roaming RAG
Author: Michael Jurasoovic
License: MIT
License-File: LICENSE
Requires-Python: >=3.11
Requires-Dist: asttokens~=3.0.0
Requires-Dist: beautifulsoup4~=4.13.3
Requires-Dist: fastmcp~=0.4.1
Requires-Dist: gitpython~=3.1.44
Requires-Dist: mcp~=1.2.0
Requires-Dist: more-itertools~=10.6.0
Requires-Dist: pydantic~=2.10.6
Requires-Dist: uvicorn<1.0.0,>=0.34.0
Requires-Dist: watchdog~=6.0.0
Provides-Extra: dev
Requires-Dist: deepdiff~=8.2.0; extra == 'dev'
Requires-Dist: line-profiler~=4.2.0; extra == 'dev'
Requires-Dist: mypy~=1.15.0; extra == 'dev'
Requires-Dist: pre-commit~=4.1.0; extra == 'dev'
Requires-Dist: pytest-cov~=6.0.0; extra == 'dev'
Requires-Dist: pytest~=8.3.4; extra == 'dev'
Requires-Dist: ruff~=0.9.9; extra == 'dev'
